rick_db/__init__.py
rick_db/cache.py
rick_db/dbgrid.py
rick_db/mapper.py
rick_db/repository.py
rick_db/version.py
rick_db/__pycache__/__init__.cpython-39.pyc
rick_db/__pycache__/mapper.cpython-39.pyc
rick_db/__pycache__/repository.cpython-39.pyc
rick_db/__pycache__/version.cpython-39.pyc
rick_db/cli/__init__.py
rick_db/cli/command.py
rick_db/cli/config.py
rick_db/cli/manage.py
rick_db/cli/commands/__init__.py
rick_db/cli/commands/check.py
rick_db/cli/commands/dto.py
rick_db/cli/commands/flatten.py
rick_db/cli/commands/help.py
rick_db/cli/commands/init.py
rick_db/cli/commands/list.py
rick_db/cli/commands/migrate.py
rick_db/conn/__init__.py
rick_db/conn/connection.py
rick_db/conn/pg/__init__.py
rick_db/conn/pg/json.py
rick_db/conn/pg/postgres.py
rick_db/conn/sqlite/__init__.py
rick_db/conn/sqlite/sqlite.py
rick_db/profiler/__init__.py
rick_db/profiler/profilers.py
rick_db/sql/__init__.py
rick_db/sql/common.py
rick_db/sql/delete.py
rick_db/sql/dialect.py
rick_db/sql/dialects.py
rick_db/sql/insert.py
rick_db/sql/select.py
rick_db/sql/update.py
rick_db/util/__init__.py
rick_db/util/console.py
rick_db/util/metadata.py
rick_db/util/migrations.py
rick_db/util/pg/__init__.py
rick_db/util/pg/metadata.py
rick_db/util/pg/migrations.py
rick_db/util/sqlite/__init__.py
rick_db/util/sqlite/metadata.py
rick_db/util/sqlite/migrations.py
tests/__init__.py
tests/config.py
tests/dbgrid.py
tests/pgsql_test_repository.py
tests/repository.py
tests/sqlite_test_repository.py
tests/test_pgsql_dbgrid.py
tests/test_pgsql_repository.py
tests/test_record.py
tests/test_sqlite_dbgrid.py
tests/test_sqlite_repository.py
tests/conn/__init__.py
tests/conn/pg/__init__.py
tests/conn/pg/test_postgres.py
tests/conn/sqlite/__init__.py
tests/conn/sqlite/test_sqlite3.py
tests/sql/__init__.py
tests/sql/test_delete.py
tests/sql/test_dialects.py
tests/sql/test_insert.py
tests/sql/test_select.py
tests/sql/test_update.py
tests/util/__init__.py
tests/util/migrations.py
tests/util/pg/__init__.py
rick_db-1.0.1.dist-info/LICENSE
rick_db-1.0.1.dist-info/METADATA
rick_db-1.0.1.dist-info/WHEEL
rick_db-1.0.1.dist-info/entry_points.txt
rick_db-1.0.1.dist-info/top_level.txt
rick_db-1.0.1.dist-info/RECORD
