Metadata-Version: 2.1
Name: rick-db
Version: 1.0.1
Summary: SQL database layer
Home-page: https://github.com/oddbit-project/rick_db
Author: Joao Pinheiro
Author-email: 
License: MIT
Platform: UNKNOWN
Classifier: Development Status :: 4 - Beta
Classifier: Intended Audience :: Developers
Classifier: License :: OSI Approved :: MIT License
Classifier: Programming Language :: Python :: 3
Classifier: Programming Language :: Python :: 3.8
Classifier: Programming Language :: Python :: 3.9
Classifier: Programming Language :: Python :: 3.10
Classifier: Programming Language :: SQL
Classifier: Topic :: Database
Classifier: Topic :: Software Development :: Libraries :: Application Frameworks
Classifier: Topic :: Software Development :: Libraries :: Python Modules
Requires-Python: >=3.7
Requires-Dist: psycopg2 (>=2.8.6)
